{
  "_class": "group",
  "booleanOperation": -1,
  "clippingMaskMode": 0,
  "do_objectID": "1C5EF79A-717D-4758-A8FB-0BF0BD730EBE",
  "exportOptions": {
    "_class": "exportOptions",
    "do_objectID": "87F2EEB7-014B-438E-9C01-8BC4C1513F00",
    "exportFormats": [
    ],
    "includedLayerIds": [
    ],
    "layerOptions": 0,
    "shouldTrim": false
  },
  "frame": {
    "_class": "rect",
    "constrainProportions": false,
    "do_objectID": "EA3604CC-5CCF-4EF4-A5A7-60C52A1DAD40",
    "height": 24,
    "width": 24,
    "x": 0,
    "y": 0
  },
  "hasClickThrough": false,
  "hasClippingMask": false,
  "isFixedToViewport": false,
  "isFlippedHorizontal": false,
  "isFlippedVertical": false,
  "isLocked": false,
  "isVisible": true,
  "layerListExpandedType": 0,
  "layers": [
    {
      "class": "shapePath",
      "id": "FCF844A0-2D02-4456-994C-7456104873DD"
    },
    {
      "class": "shapePath",
      "id": "F1036179-D211-4C1F-A3E5-0DF82C054DB0"
    }
  ],
  "name": "Group 3",
  "nameIsFixed": false,
  "resizingConstraint": 63,
  "resizingType": 0,
  "rotation": 0,
  "shouldBreakMaskChain": false,
  "style": {
    "_class": "style",
    "do_objectID": "39B36652-EFE3-461C-9AE8-13DF4CCE8D4B",
    "endMarkerType": 0,
    "miterLimit": 10,
    "startMarkerType": 0,
    "windingRule": 1
  }
}