{
  "_class": "group",
  "booleanOperation": -1,
  "clippingMaskMode": 0,
  "do_objectID": "D441E253-7379-4F8F-AEF5-860AF12D6EEE",
  "exportOptions": {
    "_class": "exportOptions",
    "do_objectID": "1E020569-2CF3-4054-B520-30FBC00FA20A",
    "exportFormats": [
    ],
    "includedLayerIds": [
    ],
    "layerOptions": 0,
    "shouldTrim": false
  },
  "frame": {
    "_class": "rect",
    "constrainProportions": false,
    "do_objectID": "57776DD5-769F-44E0-A7CB-B55520975230",
    "height": 271,
    "width": 359,
    "x": 8,
    "y": 324
  },
  "hasClickThrough": false,
  "hasClippingMask": false,
  "isFixedToViewport": false,
  "isFlippedHorizontal": false,
  "isFlippedVertical": false,
  "isLocked": false,
  "isVisible": true,
  "layerListExpandedType": 2,
  "layers": [
    {
      "class": "rectangle",
      "id": "678BFB67-8373-4D27-8B79-EAC1B13F9182"
    },
    {
      "class": "bitmap",
      "id": "DD50A3D1-2139-4C07-AEDC-E2584384D172"
    }
  ],
  "name": "map",
  "nameIsFixed": true,
  "resizingConstraint": 63,
  "resizingType": 0,
  "rotation": 0,
  "shouldBreakMaskChain": false,
  "style": {
    "_class": "style",
    "do_objectID": "19C58281-8011-4AC1-A83B-A66BECADE427",
    "endMarkerType": 0,
    "miterLimit": 10,
    "startMarkerType": 0,
    "windingRule": 1
  },
  "userInfo": {
    "com.animaapp.stc-sketch-plugin": {
      "kModelPropertiesKey": {
      }
    }
  }
}