{
  "_class": "symbolInstance",
  "booleanOperation": -1,
  "clippingMaskMode": 0,
  "do_objectID": "418482CC-1737-40A5-A93F-1C39DC22B09A",
  "exportOptions": {
    "_class": "exportOptions",
    "do_objectID": "86D95FA4-987D-4341-8D9A-704FF2D60F2F",
    "exportFormats": [
    ],
    "includedLayerIds": [
    ],
    "layerOptions": 0,
    "shouldTrim": false
  },
  "frame": {
    "_class": "rect",
    "constrainProportions": false,
    "do_objectID": "80C20703-C97A-4333-9ACB-E7AD0DD01194",
    "height": 32,
    "width": 32,
    "x": 288,
    "y": 373
  },
  "hasClippingMask": false,
  "horizontalSpacing": 0,
  "isFixedToViewport": false,
  "isFlippedHorizontal": false,
  "isFlippedVertical": false,
  "isLocked": false,
  "isVisible": true,
  "layerListExpandedType": 0,
  "name": "wireframe / icon / location copy",
  "nameIsFixed": false,
  "overrideValues": [
    {
      "_class": "overrideValue",
      "do_objectID": "5314F38C-4F97-48E4-B198-E95E1B9F3D49",
      "overrideName": "F9AF55BE-3F3C-4384-850E-C7F916A6CEB2_stringValue",
      "value": "4"
    }
  ],
  "resizingConstraint": 63,
  "resizingType": 0,
  "rotation": 0,
  "scale": 1,
  "shouldBreakMaskChain": false,
  "style": {
    "_class": "style",
    "do_objectID": "0A3DBE43-FEC4-46B1-802E-CC60EFE1B480",
    "endMarkerType": 0,
    "miterLimit": 10,
    "startMarkerType": 0,
    "windingRule": 1
  },
  "symbolID": "7E86D293-03A0-476A-AA93-A6FEE87BEEB9",
  "userInfo": {
    "com.animaapp.stc-sketch-plugin": {
      "kModelPropertiesKey": {
      }
    }
  },
  "verticalSpacing": 0
}