{
  "_class": "text",
  "attributedString": {
    "_class": "attributedString",
    "attributes": [
      {
        "_class": "stringAttribute",
        "attributes": {
          "MSAttributedStringColorAttribute": {
            "_class": "color",
            "alpha": 1,
            "blue": 0.9950678944587708,
            "green": 0.07292387634515762,
            "red": 0.5637727975845337
          },
          "MSAttributedStringFontAttribute": {
            "_class": "fontDescriptor",
            "attributes": {
              "name": "Avenir-Heavy",
              "size": 21
            }
          },
          "kerning": -0.18375,
          "paragraphStyle": {
            "_class": "paragraphStyle",
            "alignment": 0,
            "allowsDefaultTighteningForTruncation": 0,
            "baseWritingDirection": 0
          },
          "textStyleVerticalAlignmentKey": 0
        },
        "length": 132,
        "location": 0
      }
    ],
    "string": "when user doesn’t give access to the current location:\n- default location set to Alexa\n- location pin always fixed to centre of map\n"
  },
  "automaticallyDrawOnUnderlyingPath": false,
  "booleanOperation": -1,
  "clippingMaskMode": 0,
  "do_objectID": "E0BBB216-A2CD-4F4C-B3E1-28D0F5633AF4",
  "dontSynchroniseWithSymbol": false,
  "exportOptions": {
    "_class": "exportOptions",
    "do_objectID": "48EDFC4A-6D7D-4495-A956-B861CBF8F069",
    "exportFormats": [
    ],
    "includedLayerIds": [
    ],
    "layerOptions": 0,
    "shouldTrim": false
  },
  "frame": {
    "_class": "rect",
    "constrainProportions": false,
    "do_objectID": "BEE2494A-6530-4832-9AFA-0C059BF5559B",
    "height": 174,
    "width": 375,
    "x": 714,
    "y": 4211
  },
  "glyphBounds": "{{0, 5}, {370, 137}}",
  "hasClippingMask": false,
  "isFixedToViewport": false,
  "isFlippedHorizontal": false,
  "isFlippedVertical": false,
  "isLocked": false,
  "isVisible": true,
  "layerListExpandedType": 0,
  "lineSpacingBehaviour": 2,
  "name": "when user doesn’t gi",
  "nameIsFixed": false,
  "resizingConstraint": 63,
  "resizingType": 0,
  "rotation": 0,
  "shouldBreakMaskChain": false,
  "style": {
    "_class": "style",
    "do_objectID": "167430DB-ED4D-45EA-A732-E69B25A4898D",
    "endMarkerType": 0,
    "miterLimit": 10,
    "startMarkerType": 0,
    "textStyle": {
      "_class": "textStyle",
      "do_objectID": "3BE36434-AD80-4F6B-BB6E-05E36024C4D3",
      "encodedAttributes": {
        "MSAttributedStringColorAttribute": {
          "_class": "color",
          "alpha": 1,
          "blue": 0.9950678944587708,
          "green": 0.07292387634515762,
          "red": 0.5637727975845337
        },
        "MSAttributedStringFontAttribute": {
          "_class": "fontDescriptor",
          "attributes": {
            "name": "Avenir-Heavy",
            "size": 21
          }
        },
        "kerning": -0.18375,
        "paragraphStyle": {
          "_class": "paragraphStyle",
          "alignment": 0,
          "allowsDefaultTighteningForTruncation": 0,
          "baseWritingDirection": 0
        },
        "textStyleVerticalAlignmentKey": 0
      },
      "verticalAlignment": 0
    },
    "windingRule": 1
  },
  "textBehaviour": 1
}