{
  "_class": "group",
  "booleanOperation": -1,
  "clippingMaskMode": 0,
  "do_objectID": "A5E8FA64-1E58-41D2-AAD1-2282F5A98DB1",
  "exportOptions": {
    "_class": "exportOptions",
    "exportFormats": [
    ],
    "includedLayerIds": [
    ],
    "layerOptions": 0,
    "shouldTrim": false
  },
  "frame": {
    "_class": "rect",
    "constrainProportions": false,
    "height": 208,
    "width": 359,
    "x": 0,
    "y": 0
  },
  "hasClickThrough": false,
  "hasClippingMask": false,
  "isFixedToViewport": false,
  "isFlippedHorizontal": false,
  "isFlippedVertical": false,
  "isLocked": false,
  "isVisible": true,
  "layerListExpandedType": 2,
  "layers": [
    {
      "class": "rectangle",
      "id": "9C347780-6656-4FBB-86D9-1493D31BEDBF"
    },
    {
      "class": "text",
      "id": "3E12E60E-BF43-43AF-91EB-F8C2A047939A"
    },
    {
      "class": "text",
      "id": "FD0B88AD-7D37-40D7-8948-A1085078C412"
    },
    {
      "class": "group",
      "id": "94C92015-6727-416E-9BFC-B59B16DF8C52"
    },
    {
      "class": "group",
      "id": "3B6E6D6F-887B-4A92-B4AF-A3A08AE5EF72"
    }
  ],
  "name": "Group 6",
  "nameIsFixed": false,
  "resizingConstraint": 63,
  "resizingType": 0,
  "rotation": 0,
  "shouldBreakMaskChain": false,
  "style": {
    "_class": "style",
    "endMarkerType": 0,
    "miterLimit": 10,
    "startMarkerType": 0,
    "windingRule": 1
  },
  "userInfo": {
    "com.animaapp.stc-sketch-plugin": {
      "kModelPropertiesKey": {
      }
    }
  }
}